font_source_serif_pro/__init__.py
font_source_serif_pro/files/LICENSE.txt
font_source_serif_pro/files/SourceSerifPro-Black.otf
font_source_serif_pro/files/SourceSerifPro-Black.ttf
font_source_serif_pro/files/SourceSerifPro-BlackIt.otf
font_source_serif_pro/files/SourceSerifPro-BlackIt.ttf
font_source_serif_pro/files/SourceSerifPro-Bold.otf
font_source_serif_pro/files/SourceSerifPro-Bold.ttf
font_source_serif_pro/files/SourceSerifPro-BoldIt.otf
font_source_serif_pro/files/SourceSerifPro-BoldIt.ttf
font_source_serif_pro/files/SourceSerifPro-ExtraLight.otf
font_source_serif_pro/files/SourceSerifPro-ExtraLight.ttf
font_source_serif_pro/files/SourceSerifPro-ExtraLightIt.otf
font_source_serif_pro/files/SourceSerifPro-ExtraLightIt.ttf
font_source_serif_pro/files/SourceSerifPro-It.otf
font_source_serif_pro/files/SourceSerifPro-It.ttf
font_source_serif_pro/files/SourceSerifPro-Light.otf
font_source_serif_pro/files/SourceSerifPro-Light.ttf
font_source_serif_pro/files/SourceSerifPro-LightIt.otf
font_source_serif_pro/files/SourceSerifPro-LightIt.ttf
font_source_serif_pro/files/SourceSerifPro-Regular.otf
font_source_serif_pro/files/SourceSerifPro-Regular.ttf
font_source_serif_pro/files/SourceSerifPro-Semibold.otf
font_source_serif_pro/files/SourceSerifPro-Semibold.ttf
font_source_serif_pro/files/SourceSerifPro-SemiboldIt.otf
font_source_serif_pro/files/SourceSerifPro-SemiboldIt.ttf
font_source_serif_pro-0.0.1.dist-info/DESCRIPTION.rst
font_source_serif_pro-0.0.1.dist-info/METADATA
font_source_serif_pro-0.0.1.dist-info/RECORD
font_source_serif_pro-0.0.1.dist-info/WHEEL
font_source_serif_pro-0.0.1.dist-info/entry_points.txt
font_source_serif_pro-0.0.1.dist-info/metadata.json
font_source_serif_pro-0.0.1.dist-info/top_level.txt
